ei/__init__.py
ei/embed.py
ei/hook.py
ei/patch.py
ei/patched.py
ei-0.0.14.dist-info/METADATA
ei-0.0.14.dist-info/WHEEL
ei-0.0.14.dist-info/licenses/LICENSE
ei-0.0.14.dist-info/RECORD
