Metadata-Version: 2.4
Name: ei
Version: 0.0.14
Summary: Automatically embed IPython into arbitrary stack frames in traceback.
Project-URL: Homepage, https://github.com/djosix/ei
Project-URL: Bug Tracker, https://github.com/djosix/ei/issues
Author-email: Yuankui Lee <toregenerate@gmail.com>
License: MIT
License-File: LICENSE
Classifier: License :: OSI Approved :: MIT License
Classifier: Operating System :: OS Independent
Classifier: Programming Language :: Python :: 3
Requires-Python: >=3.5
Requires-Dist: ipython
